{"cameraMode":{"drawMode":0,"name":"Shaded","section":"Shading Mode"},"sceneLighting":true,"audioPlay":false,"sceneViewState":{"m_AlwaysRefresh":false,"showFog":true,"showSkybox":true,"showFlares":true,"showImageEffects":true,"showParticleSystems":true,"showVisualEffectGraphs":true,"m_FxEnabled":true},"in2DMode":false,"pivot":{"x":-22.335338592529298,"y":-8.513489723205567,"z":11.637809753417969},"rotation":{"x":0.26458683609962466,"y":-0.4762336313724518,"z":0.1528288722038269,"w":0.824596107006073},"size":29.633609771728517,"orthographic":false}